negara/__init__.py
negara/countries.py
countries_info-0.0.1.dist-info/LICENSE
countries_info-0.0.1.dist-info/METADATA
countries_info-0.0.1.dist-info/WHEEL
countries_info-0.0.1.dist-info/top_level.txt
countries_info-0.0.1.dist-info/RECORD
