Metadata-Version: 2.1
Name: countries-info
Version: 0.0.1
Summary: Simple library to get information about country
Home-page: https://github.com/iqbull2244/negara
Author: iqballl
Author-email: <rafiiqbal2407@gmail.com>
Keywords: countries,negara
Classifier: Development Status :: 1 - Planning
License-File: LICENSE
